django_handy_utils/__init__.py
django_handy_utils/celery.py
django_handy_utils/db.py
django_handy_utils/filters/__init__.py
django_handy_utils/models/__init__.py
django_handy_utils/models/mixins.py
django_handy_utils/permissions.py
django_handy_utils/serialize.py
django_handy_utils/views/__init__.py
django_handy_utils/views/errors.py
django_handy_utils/views/mixins.py
django_handy_utils-1.1.4.dist-info/LICENSE.md
django_handy_utils-1.1.4.dist-info/WHEEL
django_handy_utils-1.1.4.dist-info/METADATA
django_handy_utils-1.1.4.dist-info/RECORD
